langchain_token_usage/__init__.py
langchain_token_usage/handlers/__init__.py
langchain_token_usage/handlers/local_handler.py
langchain_token_usage/handlers/openai_handler.py
langchain_token_usage/handlers/timer.py
langchain_token_usage/py.typed
langchain_token_usage/reporters/__init__.py
langchain_token_usage/reporters/base.py
langchain_token_usage/reporters/cloudwatch.py
langchain_token_usage/reporters/localstats.py
langchain_token_usage-0.1.1.dist-info/LICENSE
langchain_token_usage-0.1.1.dist-info/METADATA
langchain_token_usage-0.1.1.dist-info/WHEEL
langchain_token_usage-0.1.1.dist-info/RECORD
