Metadata-Version: 2.1
Name: langchain-token-usage
Version: 0.1.1
Summary: Langchain Token Usage
Home-page: https://github.com/mrtj/langchain-token-usage
License: MIT
Author: Janos Tolgyesi
Author-email: janos.tolgyesi@gmail.com
Requires-Python: >=3.8.1,<4.0
Classifier: Development Status :: 3 - Alpha
Classifier: License :: OSI Approved :: MIT License
Classifier: Programming Language :: Python :: 3
Classifier: Programming Language :: Python :: 3.9
Classifier: Programming Language :: Python :: 3.10
Classifier: Programming Language :: Python :: 3.11
Classifier: Programming Language :: Python :: 3.12
Requires-Dist: langchain (>=0.0.351,<0.1.0)
Requires-Dist: urllib3 (>=1.25.4,<1.27)
Project-URL: Changelog, https://github.com/mrtj/langchain-token-usage/releases
Project-URL: Documentation, https://langchain-token-usage.readthedocs.io
Project-URL: Repository, https://github.com/mrtj/langchain-token-usage
